zoho_mcp/__init__.py
zoho_mcp/auth_cli.py
zoho_mcp/server.py
zoho_mcp/zoho_auth.py
zoho_mcp/zoho_tools.py
zoho_crm_mcp-0.1.1.dist-info/METADATA
zoho_crm_mcp-0.1.1.dist-info/WHEEL
zoho_crm_mcp-0.1.1.dist-info/entry_points.txt
zoho_crm_mcp-0.1.1.dist-info/licenses/LICENSE
zoho_crm_mcp-0.1.1.dist-info/RECORD
