Metadata-Version: 2.4
Name: zoho-crm-mcp
Version: 0.1.1
Summary: Model Context Protocol server for Zoho CRM integration
Author-email: Your Name <your.email@example.com>
License-File: LICENSE
Requires-Python: >=3.11
Requires-Dist: fastmcp>=0.1.0
Requires-Dist: pydantic>=2.0.0
Requires-Dist: python-dotenv>=1.0.0
Requires-Dist: requests>=2.31.0
